df_xfyun_speech/__init__.py
df_xfyun_speech-0.1.0.dist-info/LICENSE
df_xfyun_speech-0.1.0.dist-info/METADATA
df_xfyun_speech-0.1.0.dist-info/WHEEL
df_xfyun_speech-0.1.0.dist-info/top_level.txt
df_xfyun_speech-0.1.0.dist-info/RECORD
